hotspell/__init__.py
hotspell/heatwaves.py
hotspell/indices.py
hotspell/metrics.py
hotspell/utils.py
hotspell/datasets/daily_windows_with_length_15.pickle
hotspell/datasets/daily_windows_with_length_3.pickle
hotspell-0.1.5.8.dist-info/LICENSE
hotspell-0.1.5.8.dist-info/METADATA
hotspell-0.1.5.8.dist-info/WHEEL
hotspell-0.1.5.8.dist-info/top_level.txt
hotspell-0.1.5.8.dist-info/RECORD
