Metadata-Version: 2.1
Name: hotspell
Version: 0.1.5.8
Summary: Detect heat waves from weather station data
Home-page: https://github.com/agathangelidis/hotspell
Author: Ilias Agathangelidis
License-File: LICENSE
Requires-Dist: numpy
Requires-Dist: pandas
